kuroboros/__init__.py
kuroboros/config.py
kuroboros/controller.py
kuroboros/exceptions.py
kuroboros/extended_api.py
kuroboros/group_version_info.py
kuroboros/logger.py
kuroboros/operator.py
kuroboros/reconciler.py
kuroboros/utils.py
kuroboros/webhook.py
kuroboros/webhook_server.py
kuroboros/cli/__init__.py
kuroboros/cli/build.py
kuroboros/cli/deploy.py
kuroboros/cli/generate.py
kuroboros/cli/main.py
kuroboros/cli/new.py
kuroboros/cli/utils.py
kuroboros/cli/templates/__init__.py
kuroboros/cli/templates/__pycache__/__init__.cpython-310.pyc
kuroboros/cli/templates/__pycache__/__init__.cpython-312.pyc
kuroboros/cli/templates/__pycache__/__init__.cpython-313.pyc
kuroboros/cli/templates/generate/kustomization.yaml.j2
kuroboros/cli/templates/generate/crd/crd.yaml.j2
kuroboros/cli/templates/generate/deployment/metrics-service.yaml.j2
kuroboros/cli/templates/generate/deployment/operator-config.yaml.j2
kuroboros/cli/templates/generate/deployment/operator-deployment.yaml.j2
kuroboros/cli/templates/generate/deployment/webhook-service.yaml.j2
kuroboros/cli/templates/generate/rbac/leader-election-role-binding.yaml.j2
kuroboros/cli/templates/generate/rbac/leader-election-role.yaml.j2
kuroboros/cli/templates/generate/rbac/operator-role-binding.yaml.j2
kuroboros/cli/templates/generate/rbac/operator-role.yaml.j2
kuroboros/cli/templates/generate/rbac/service-account.yaml.j2
kuroboros/cli/templates/generate/webhooks/mutation-webhook-config.yaml.j2
kuroboros/cli/templates/generate/webhooks/validation-webhook-config.yaml.j2
kuroboros/cli/templates/new/controller/group_version.py.j2
kuroboros/cli/templates/new/controller/reconciler.py.j2
kuroboros/cli/templates/new/controller/types.py.j2
kuroboros/cli/templates/new/project/docker.j2
kuroboros/cli/templates/new/project/operator.toml.j2
kuroboros/cli/templates/new/project/pyproject.toml.j2
kuroboros/cli/templates/new/webhooks/mutation.py.j2
kuroboros/cli/templates/new/webhooks/validation.py.j2
kuroboros/schema/__init__.py
kuroboros-1.0.6.dist-info/licenses/LICENSE
kuroboros-1.0.6.dist-info/METADATA
kuroboros-1.0.6.dist-info/WHEEL
kuroboros-1.0.6.dist-info/entry_points.txt
kuroboros-1.0.6.dist-info/top_level.txt
kuroboros-1.0.6.dist-info/RECORD
