Metadata-Version: 2.4
Name: kuroboros
Version: 1.0.6
Summary: A kubernetes operator framework
Author: Juan Edwards
Project-URL: Homepage, https://github.com/jedwards94/kuroboros
Requires-Python: >=3.13
License-File: LICENSE
Requires-Dist: click==8.2.0
Requires-Dist: kubernetes==32.0.1
Requires-Dist: inflect==7.5.0
Requires-Dist: jinja2==3.1.6
Requires-Dist: prometheus-client==0.21.1
Requires-Dist: falcon==4.0.2
Requires-Dist: gunicorn==23.0.0
Requires-Dist: jsonpatch==1.33
Requires-Dist: case-converter==1.2.0
Requires-Dist: tomlkit==0.13.3
Dynamic: license-file
